pygopher/interfaces.py
pygopher_interfaces-0.1.3.dist-info/METADATA
pygopher_interfaces-0.1.3.dist-info/WHEEL
pygopher_interfaces-0.1.3.dist-info/licenses/LICENSE
pygopher_interfaces-0.1.3.dist-info/RECORD
