Metadata-Version: 2.1
Name: pygopher-interfaces
Version: 0.1.3
Summary: Go-style interfaces for Python
Project-URL: Changelog, https://github.com/mrogaski/pygopher-interfaces/blob/main/CHANGELOG.rst
Project-URL: Bug Tracker, https://github.com/mrogaski/pygopher-interfaces/issues
Project-URL: Source Code, https://github.com/mrogaski/pygopher-interfaces
Author-email: Mark Rogaski <mrogaski@pobox.com>
Maintainer-email: Mark Rogaski <mrogaski@pobox.com>
License-File: LICENSE
Classifier: Development Status :: 4 - Beta
Classifier: Intended Audience :: Developers
Classifier: License :: OSI Approved :: MIT License
Classifier: Programming Language :: Python :: 3.7
Classifier: Programming Language :: Python :: 3.8
Classifier: Programming Language :: Python :: 3.9
Classifier: Programming Language :: Python :: 3.10
Classifier: Typing :: Typed
Requires-Python: >=3.7
Requires-Dist: importlib-metadata; python_version < '3.8'
Provides-Extra: dev
Requires-Dist: pygopher-interfaces[docs,linters,tests,typing]; extra == 'dev'
Provides-Extra: docs
Requires-Dist: sphinx; extra == 'docs'
Requires-Dist: sphinx-rtd-theme; extra == 'docs'
Provides-Extra: linters
Requires-Dist: pylint; extra == 'linters'
Provides-Extra: tests
Requires-Dist: coverage[toml]; extra == 'tests'
Requires-Dist: pytest-cov; extra == 'tests'
Requires-Dist: pytest>=7.0; extra == 'tests'
Provides-Extra: typing
Requires-Dist: mypy; extra == 'typing'
